elliptic/__init__.py
elliptic/aml.py
elliptic/client.py
elliptic/hmac.py
elliptic/sign.py
elliptic/webhook_verification.py
elliptic_python-0.9.1.dist-info/METADATA
elliptic_python-0.9.1.dist-info/WHEEL
elliptic_python-0.9.1.dist-info/RECORD
