Metadata-Version: 2.1
Name: elliptic-python
Version: 0.9.1
Summary: Elliptic SDK for Python - A Requests wrapper for connecting to Elliptic APIs
Home-page: https://developers.elliptic.co
License: Apache-2.0
Author: Elliptic
Requires-Python: >=3.8.1
Classifier: Development Status :: 5 - Production/Stable
Classifier: License :: OSI Approved :: Apache Software License
Classifier: Operating System :: OS Independent
Classifier: Programming Language :: Python :: 3
Classifier: Programming Language :: Python :: 3.9
Classifier: Programming Language :: Python :: 3.10
Classifier: Programming Language :: Python :: 3.11
Classifier: Programming Language :: Python :: 3
Classifier: Programming Language :: Python :: 3.10
Classifier: Programming Language :: Python :: 3.11
Classifier: Programming Language :: Python :: 3.7
Classifier: Programming Language :: Python :: 3.8
Classifier: Programming Language :: Python :: 3.9
Requires-Dist: cryptography (>=43.0.3,<44.0.0)
Requires-Dist: requests (>=2.20.0)
Project-URL: Repository, https://bitbucket.org/elliptic/elliptic-sdk-python
